[
	{
		"name": "Chizchia",
		"leaderName": "Chipura II",
		"adjective": ["Chizchian"],
		"startBias": ["Coast"],
		"preferredVictoryType": "Diplomatic",
		
		"startIntroPart1": ["Please rule your people of Chizchia nicely."],
		"startIntroPart2": ["Let's ride the great wave, hang out around the deepest reef!"],
		
		"declaringWar": ["You are the barrier of the mankind progression!"],
		"attacked": ["War is loss of many people's youth and nature itself."],
		"defeated": ["As long as the Chizchia stands, liberalism shall stand..."],
		"introduction": ["Let's be friend, just friend. Let's ride the great wave, hang out around the deepest reef!"],
		
		"neutralHello": ["Sup mr ambassador"],
		"neutralLetsHearIt": ["Go on."],
		"neutralNo": ["This is harmful for the enviroment."],
		"neutralYes": ["That is very good."],

		"hateHello": ["Stay away"],
		"hateLetsHearIt": ["Speak!"],
		"hateNo": ["We are not agreeing to that!"],
		"hateYes": ["That is good enough."],
		
		"afterPeace": ["This apology cannot pay for the millions of lives."],
		"tradeRequest": ["This is verified by WFTO, fair trade for workers!"],

		"outerColor": [16,16,16],
		"innerColor": [0,205,255],
		"uniques": ["[+2 Food, +1 Happiness] from every [Coast]","[-10 Happiness] from every [Barracks]","Cannot build [Worker] units"],
		"cities": ["Crimau","Dojcad","Sulos","Chpu","Achmun","Chchay","Palgos","Cavok"]
	}
]
